Metadata-Version: 2.1
Name: PastebinReaderPy
Version: 1.0.0
Summary: Python Pastebin Library for reading and running pastes
Author: Dolenko10.0Artem10.0
Author-email: artemdolenko.ua@gmail.com
Classifier: Programming Language :: Python :: 3
Classifier: License :: OSI Approved :: MIT License
Classifier: Operating System :: OS Independent
Requires-Python: >=3.6
